tonkin/__init__.py
tonkin/datastream.py
tonkin/datfile.py
tonkin/datvar.py
tonkin/fileops.py
tonkin/fixed.py
tonkin/listops.py
tonkin/packets.py
tonkin/parse.py
tonkin/values.py
tonkin/varsec.py
tonkin/verification.py
tonkin-1.0.0.dist-info/METADATA
tonkin-1.0.0.dist-info/WHEEL
tonkin-1.0.0.dist-info/top_level.txt
tonkin-1.0.0.dist-info/RECORD
